[
  {
    "address_name": "경남 양산시 원동면 서룡리 586-10",
    "category_group_code": "",
    "category_group_name": "",
    "category_name": "여행 > 공원",
    "distance": "",
    "id": "393021292",
    "phone": "",
    "place_name": "서룡공원",
    "place_url": "http://place.map.kakao.com/393021292",
    "road_address_name": "",
    "x": "128.956018445921",
    "y": "35.3377746254671"
  },
  {
    "address_name": "경남 양산시 물금읍 물금리 290-1",
    "category_group_code": "",
    "category_group_name": "",
    "category_name": "여행 > 관광,명소 > 광장",
    "distance": "",
    "id": "244496737",
    "phone": "",
    "place_name": "황산공원 중부광장",
    "place_url": "http://place.map.kakao.com/244496737",
    "road_address_name": "",
    "x": "128.9866392439806",
    "y": "35.30413244194464"
  },
  {
    "address_name": "경남 양산시 물금읍 물금리 327-11",
    "category_group_code": "PK6",
    "category_group_name": "주차장",
    "category_name": "교통,수송 > 교통시설 > 주차장",
    "distance": "",
    "id": "1950921499",
    "phone": "",
    "place_name": "황산공원 황산육교주차장",
    "place_url": "http://place.map.kakao.com/1950921499",
    "road_address_name": "",
    "x": "128.985282623302",
    "y": "35.3058380890681"
  },
  {
    "address_name": "경남 양산시 물금읍 물금리 796-2",
    "category_group_code": "PK6",
    "category_group_name": "주차장",
    "category_name": "교통,수송 > 교통시설 > 주차장 > 공영주차장",
    "distance": "",
    "id": "796937976",
    "phone": "",
    "place_name": "황산공원 서부주차장",
    "place_url": "http://place.map.kakao.com/796937976",
    "road_address_name": "",
    "x": "128.9785014808861",
    "y": "35.310148656086845"
  },
  {
    "address_name": "경남 양산시 물금읍 물금리 789-1",
    "category_group_code": "PK6",
    "category_group_name": "주차장",
    "category_name": "교통,수송 > 교통시설 > 주차장 > 공영주차장",
    "distance": "",
    "id": "27587189",
    "phone": "",
    "place_name": "황산공원 서부광장 주차장",
    "place_url": "http://place.map.kakao.com/27587189",
    "road_address_name": "",
    "x": "128.982207877554",
    "y": "35.307056444312"
  },
  {
    "address_name": "경남 양산시 물금읍 물금리 792-3",
    "category_group_code": "",
    "category_group_name": "",
    "category_name": "여행 > 관광,명소 > 광장",
    "distance": "",
    "id": "27587187",
    "phone": "",
    "place_name": "황산공원 문주광장",
    "place_url": "http://place.map.kakao.com/27587187",
    "road_address_name": "",
    "x": "128.98138009603542",
    "y": "35.307913497930194"
  },
  {
    "address_name": "경남 김해시 상동면 매리 57",
    "category_group_code": "",
    "category_group_name": "",
    "category_name": "가정,생활 > 화장실",
    "distance": "",
    "id": "836652010",
    "phone": "",
    "place_name": "매리생태공원 공중화장실",
    "place_url": "http://place.map.kakao.com/836652010",
    "road_address_name": "경남 김해시 상동면 동북로 518",
    "x": "128.967902387905",
    "y": "35.3194504053733"
  },
  {
    "address_name": "경남 양산시 물금읍 물금리 817-3",
    "category_group_code": "",
    "category_group_name": "",
    "category_name": "스포츠,레저 > 축구 > 축구장",
    "distance": "",
    "id": "27587192",
    "phone": "",
    "place_name": "황산공원 축구장",
    "place_url": "http://place.map.kakao.com/27587192",
    "road_address_name": "",
    "x": "128.98311397494555",
    "y": "35.30652612167693"
  },
  {
    "address_name": "경남 양산시 물금읍 물금리 288",
    "category_group_code": "",
    "category_group_name": "",
    "category_name": "스포츠,레저 > 농구 > 농구장",
    "distance": "",
    "id": "27587193",
    "phone": "",
    "place_name": "황산공원 농구장",
    "place_url": "http://place.map.kakao.com/27587193",
    "road_address_name": "경남 양산시 물금읍 낙동강자전거길 2634-11",
    "x": "128.9846756199162",
    "y": "35.303670860595346"
  },
  {
    "address_name": "경남 양산시 물금읍 물금리 771-13",
    "category_group_code": "CE7",
    "category_group_name": "카페",
    "category_name": "음식점 > 카페 > 커피전문점 > 컴포즈커피",
    "distance": "",
    "id": "1205872334",
    "phone": "070-7379-5378",
    "place_name": "컴포즈커피 양산황산공원점",
    "place_url": "http://place.map.kakao.com/1205872334",
    "road_address_name": "경남 양산시 물금읍 물금중앙길 34-1",
    "x": "128.98301959995032",
    "y": "35.3094149765417"
  }
]